<?xml version="1.0" encoding="UTF-8"?>
<con:soapui-project id="13ae295d-c2f7-4cf0-9ac5-6c23943d25d4" activeEnvironment="Default" name="REST Project 1" resourceRoot="" soapui-version="5.7.0" abortOnError="false" runType="SEQUENTIAL" xmlns:con="http://eviware.com/soapui/config"><con:settings><con:setting id="com.eviware.soapui.impl.wsdl.actions.iface.tools.soapui.TestRunnerAction@values-local"><![CDATA[<xml-fragment xmlns:con="http://eviware.com/soapui/config">
  <con:entry key="Report Format(s)" value=""/>
  <con:entry key="Host:Port" value=""/>
  <con:entry key="Export JUnit Results" value="false"/>
  <con:entry key="Export All" value="false"/>
  <con:entry key="Save After" value="false"/>
  <con:entry key="Add Settings" value="false"/>
  <con:entry key="WSS Password Type" value=""/>
  <con:entry key="TestSuite" value="TestSuite 1"/>
  <con:entry key="Endpoint" value=""/>
  <con:entry key="Select Report Type" value=""/>
  <con:entry key="System Properties" value=""/>
  <con:entry key="Password" value=""/>
  <con:entry key="Print Report" value="false"/>
  <con:entry key="Open Report" value="false"/>
  <con:entry key="Export JUnit Results with test properties" value="false"/>
  <con:entry key="Global Properties" value=""/>
  <con:entry key="Project Properties" value=""/>
  <con:entry key="Project Password" value=""/>
  <con:entry key="TestCase" value="Students"/>
  <con:entry key="Username" value=""/>
  <con:entry key="user-settings.xml Password" value=""/>
  <con:entry key="TestRunner Path" value=""/>
  <con:entry key="Environment" value="Default"/>
  <con:entry key="Coverage Report" value="false"/>
  <con:entry key="Enable UI" value="false"/>
  <con:entry key="Root Folder" value=""/>
  <con:entry key="Ignore Errors" value="false"/>
  <con:entry key="Domain" value=""/>
  <con:entry key="Tool Args" value=""/>
  <con:entry key="Save Project" value="false"/>
</xml-fragment>]]></con:setting></con:settings><con:interface xsi:type="con:RestService" id="29b7946a-a845-43cf-b39d-33ae427926de" wadlVersion="http://wadl.dev.java.net/2009/02" name="http://thetestingworldapi.com" type="rest" xmlns:xsi="http://www.w3.org/2001/XMLSchema-instance"><con:settings/><con:definitionCache type="TEXT" rootPart=""/><con:endpoints><con:endpoint>http://thetestingworldapi.com</con:endpoint></con:endpoints><con:resource name="AllStudentsDetails" path="/api/studentsDetails" id="a46ae2bd-c5f5-4dbe-a10e-01996f7c19a3"><con:settings/><con:parameters/><con:method name="getAllStudent" id="b6002c57-2e70-469e-837d-e9ab73996bf6" method="GET"><con:settings/><con:parameters/><con:representation type="RESPONSE"><con:mediaType>application/json; charset=utf-8</con:mediaType><con:status>200</con:status><con:params/><con:element>Response</con:element></con:representation><con:request name="GET_AllStudents" id="089c134a-91b8-4177-993c-fe05aaa1a9a3" mediaType="application/json"><con:settings><con:setting id="com.eviware.soapui.impl.wsdl.WsdlRequest@request-headers">&lt;xml-fragment/></con:setting></con:settings><con:endpoint>http://thetestingworldapi.com</con:endpoint><con:request/><con:originalUri>http://thetestingworldapi.com/api/studentsDetails</con:originalUri><con:credentials><con:authType>No Authorization</con:authType></con:credentials><con:jmsConfig JMSDeliveryMode="PERSISTENT"/><con:jmsPropertyConfig/><con:parameters/></con:request></con:method></con:resource></con:interface><con:interface xsi:type="con:RestService" id="9bffb98e-3d6e-4d0e-a189-ed1d67a2203f" wadlVersion="http://wadl.dev.java.net/2009/02" name="http://thetestingworldapi.com" type="rest" xmlns:xsi="http://www.w3.org/2001/XMLSchema-instance"><con:settings/><con:definitionCache type="TEXT" rootPart=""/><con:endpoints><con:endpoint>http://thetestingworldapi.com</con:endpoint></con:endpoints><con:resource name="getStudent" path="/api/studentsDetails/{id}" id="77758599-49fd-40ba-b44d-2961239f2973"><con:settings/><con:parameters><con:parameter><con:name>id</con:name><con:value>1016618</con:value><con:style>TEMPLATE</con:style><con:default>1016618</con:default></con:parameter></con:parameters><con:method name="getStudent" id="11444c73-86a5-479b-b88f-714bfc213a70" method="GET"><con:settings/><con:parameters/><con:representation type="FAULT"><con:mediaType>text/html; charset=utf-8</con:mediaType><con:status>404</con:status><con:params/><con:element>html</con:element></con:representation><con:representation type="RESPONSE"><con:mediaType xsi:nil="true"/><con:status>0</con:status><con:params/><con:element>data</con:element></con:representation><con:representation type="RESPONSE"><con:mediaType xsi:nil="true"/><con:status>0</con:status><con:params/><con:element>data</con:element></con:representation><con:representation type="RESPONSE"><con:mediaType xsi:nil="true"/><con:status>0</con:status><con:params/><con:element>data</con:element></con:representation><con:representation type="RESPONSE"><con:mediaType xsi:nil="true"/><con:status>0</con:status><con:params/><con:element>data</con:element></con:representation><con:representation type="RESPONSE"><con:mediaType xsi:nil="true"/><con:status>0</con:status><con:params/><con:element>data</con:element></con:representation><con:representation type="RESPONSE"><con:mediaType xsi:nil="true"/><con:status>0</con:status><con:params/><con:element>data</con:element></con:representation><con:representation type="FAULT"><con:mediaType>application/json; charset=utf-8</con:mediaType><con:status>400</con:status><con:params/></con:representation><con:representation type="RESPONSE"><con:mediaType>application/json; charset=utf-8</con:mediaType><con:status>200</con:status><con:params/></con:representation><con:request name="GET_SpecificStudent" id="8f26412b-64b2-4890-a4eb-59379cbbb5b4" mediaType="application/json"><con:settings><con:setting id="com.eviware.soapui.impl.wsdl.WsdlRequest@request-headers">&lt;xml-fragment/></con:setting></con:settings><con:endpoint>http://thetestingworldapi.com</con:endpoint><con:request/><con:originalUri>http://thetestingworldapi.com//studentsDetails/1016618</con:originalUri><con:credentials><con:authType>No Authorization</con:authType></con:credentials><con:jmsConfig JMSDeliveryMode="PERSISTENT"/><con:jmsPropertyConfig/><con:parameters><entry key="id" value="1016627" xmlns="http://eviware.com/soapui/config"/></con:parameters><con:parameterOrder><con:entry>id</con:entry></con:parameterOrder></con:request></con:method></con:resource></con:interface><con:interface xsi:type="con:RestService" id="0b5de4c6-9ad9-45f4-a832-c1766c80819b" wadlVersion="http://wadl.dev.java.net/2009/02" name="http://thetestingworldapi.com" type="rest" xmlns:xsi="http://www.w3.org/2001/XMLSchema-instance"><con:settings/><con:definitionCache type="TEXT" rootPart=""/><con:endpoints><con:endpoint>http://thetestingworldapi.com</con:endpoint></con:endpoints><con:resource name="CreateStudent" path="/api/studentsDetails" id="7dcd3a15-9ac2-4554-b780-9e7748d8dce2"><con:settings/><con:parameters/><con:method name="createStudent" id="062e9398-a586-431d-a6aa-ef0c648331f7" method="POST"><con:settings/><con:parameters/><con:representation type="RESPONSE"><con:mediaType>application/json; charset=utf-8</con:mediaType><con:status>201</con:status><con:params/><con:element xmlns:stud="http://thetestingworldapi.com/api/studentsDetails">stud:Response</con:element></con:representation><con:representation type="REQUEST"><con:mediaType>application/json</con:mediaType><con:params/></con:representation><con:representation type="FAULT"><con:mediaType>application/json; charset=utf-8</con:mediaType><con:status>500</con:status><con:params/><con:element xmlns:stud="http://thetestingworldapi.com/api/studentsDetails">stud:Fault</con:element></con:representation><con:request name="CreateStudent" id="cdbfc28a-4740-46f9-8ec6-16778ec45414" mediaType="application/json" postQueryString="false"><con:settings><con:setting id="com.eviware.soapui.impl.wsdl.WsdlRequest@request-headers">&lt;xml-fragment/></con:setting></con:settings><con:endpoint>http://thetestingworldapi.com</con:endpoint><con:request>{
  "id": 1225,
  "first_name": "Ramesh",
  "middle_name": "suresh",
  "last_name": "doubleD",
  "date_of_birth": "20Aug1994"
}</con:request><con:originalUri>http://thetestingworldapi.com/api/studentsDetails</con:originalUri><con:credentials><con:authType>No Authorization</con:authType></con:credentials><con:jmsConfig JMSDeliveryMode="PERSISTENT"/><con:jmsPropertyConfig/><con:parameters/></con:request></con:method></con:resource></con:interface><con:interface xsi:type="con:RestService" id="c306c69e-135b-476c-b96d-8903df83e9d1" wadlVersion="http://wadl.dev.java.net/2009/02" name="http://thetestingworldapi.com" type="rest" xmlns:xsi="http://www.w3.org/2001/XMLSchema-instance"><con:settings/><con:definitionCache type="TEXT" rootPart=""/><con:endpoints><con:endpoint>http://thetestingworldapi.com</con:endpoint></con:endpoints><con:resource name="UpdateStudent" path="/api/studentsDetails/{id}" id="1b5342df-be04-4874-9a87-3612d79f3c7a"><con:settings/><con:parameters><con:parameter><con:name>id</con:name><con:value>id</con:value><con:style>TEMPLATE</con:style><con:default>id</con:default><con:path xsi:nil="true"/><con:description xsi:nil="true"/></con:parameter></con:parameters><con:method name="updateStudent" id="f2eb7c0c-d33b-45a9-81a3-264a08b04276" method="PUT"><con:settings/><con:parameters/><con:representation type="FAULT"><con:mediaType>application/json; charset=utf-8</con:mediaType><con:status>400</con:status><con:params/><con:element xmlns:id="http://thetestingworldapi.com/api/studentsDetails/id">id:Fault</con:element></con:representation><con:representation type="REQUEST"><con:mediaType>application/json</con:mediaType><con:params/></con:representation><con:representation type="FAULT"><con:mediaType xsi:nil="true"/><con:status>400</con:status><con:params/><con:element>data</con:element></con:representation><con:representation type="FAULT"><con:mediaType xsi:nil="true"/><con:status>400</con:status><con:params/><con:element>data</con:element></con:representation><con:representation type="RESPONSE"><con:mediaType>application/json; charset=utf-8</con:mediaType><con:status>200</con:status><con:params/><con:element xmlns:id="http://thetestingworldapi.com/api/studentsDetails/id">id:Response</con:element></con:representation><con:representation type="FAULT"><con:mediaType xsi:nil="true"/><con:status>400</con:status><con:params/><con:element>data</con:element></con:representation><con:representation type="FAULT"><con:mediaType xsi:nil="true"/><con:status>400</con:status><con:params/><con:element>data</con:element></con:representation><con:representation type="FAULT"><con:mediaType xsi:nil="true"/><con:status>400</con:status><con:params/><con:element>data</con:element></con:representation><con:representation type="FAULT"><con:mediaType xsi:nil="true"/><con:status>400</con:status><con:params/><con:element>data</con:element></con:representation><con:representation type="FAULT"><con:mediaType xsi:nil="true"/><con:status>400</con:status><con:params/><con:element>data</con:element></con:representation><con:representation type="FAULT"><con:mediaType xsi:nil="true"/><con:status>400</con:status><con:params/><con:element>data</con:element></con:representation><con:representation type="FAULT"><con:mediaType xsi:nil="true"/><con:status>400</con:status><con:params/><con:element>data</con:element></con:representation><con:representation type="FAULT"><con:mediaType xsi:nil="true"/><con:status>400</con:status><con:params/><con:element>data</con:element></con:representation><con:representation type="FAULT"><con:mediaType xsi:nil="true"/><con:status>404</con:status><con:params/><con:element>data</con:element></con:representation><con:representation type="FAULT"><con:mediaType xsi:nil="true"/><con:status>404</con:status><con:params/><con:element>data</con:element></con:representation><con:representation type="FAULT"><con:mediaType xsi:nil="true"/><con:status>400</con:status><con:params/><con:element>data</con:element></con:representation><con:representation type="FAULT"><con:mediaType xsi:nil="true"/><con:status>400</con:status><con:params/><con:element>data</con:element></con:representation><con:representation type="FAULT"><con:mediaType xsi:nil="true"/><con:status>400</con:status><con:params/><con:element>data</con:element></con:representation><con:representation type="FAULT"><con:mediaType xsi:nil="true"/><con:status>400</con:status><con:params/><con:element>data</con:element></con:representation><con:representation type="FAULT"><con:mediaType xsi:nil="true"/><con:status>400</con:status><con:params/><con:element>data</con:element></con:representation><con:representation type="FAULT"><con:mediaType xsi:nil="true"/><con:status>400</con:status><con:params/><con:element>data</con:element></con:representation><con:representation type="FAULT"><con:mediaType xsi:nil="true"/><con:status>400</con:status><con:params/><con:element>data</con:element></con:representation><con:representation type="FAULT"><con:mediaType xsi:nil="true"/><con:status>400</con:status><con:params/><con:element>data</con:element></con:representation><con:representation type="FAULT"><con:mediaType xsi:nil="true"/><con:status>400</con:status><con:params/><con:element>data</con:element></con:representation><con:representation type="FAULT"><con:mediaType xsi:nil="true"/><con:status>400</con:status><con:params/><con:element>data</con:element></con:representation><con:representation type="FAULT"><con:mediaType xsi:nil="true"/><con:status>404</con:status><con:params/><con:element>data</con:element></con:representation><con:representation type="FAULT"><con:mediaType xsi:nil="true"/><con:status>400</con:status><con:params/><con:element>data</con:element></con:representation><con:representation type="FAULT"><con:mediaType xsi:nil="true"/><con:status>400</con:status><con:params/><con:element>data</con:element></con:representation><con:representation type="FAULT"><con:mediaType xsi:nil="true"/><con:status>400</con:status><con:params/><con:element>data</con:element></con:representation><con:representation type="FAULT"><con:mediaType xsi:nil="true"/><con:status>400</con:status><con:params/><con:element>data</con:element></con:representation><con:representation type="FAULT"><con:mediaType xsi:nil="true"/><con:status>400</con:status><con:params/><con:element>data</con:element></con:representation><con:representation type="FAULT"><con:mediaType xsi:nil="true"/><con:status>400</con:status><con:params/><con:element>data</con:element></con:representation><con:representation type="FAULT"><con:mediaType xsi:nil="true"/><con:status>404</con:status><con:params/><con:element>data</con:element></con:representation><con:request name="UpdateStrudent" id="31596c05-c3e3-4dba-9f47-e0fcd89325bb" mediaType="application/json" postQueryString="false"><con:settings><con:setting id="com.eviware.soapui.impl.wsdl.WsdlRequest@request-headers">&lt;xml-fragment/></con:setting></con:settings><con:endpoint>http://thetestingworldapi.com</con:endpoint><con:request>{
   "id": 1016683,
   "first_name": "Ramesh",
   "middle_name": "abc",
   "last_name": "doubleD",
   "date_of_birth": "20Aug1994"
}</con:request><con:originalUri>http://thetestingworldapi.com/api/studentsDetails/id</con:originalUri><con:credentials><con:authType>No Authorization</con:authType></con:credentials><con:jmsConfig JMSDeliveryMode="PERSISTENT"/><con:jmsPropertyConfig/><con:parameters><entry key="id" value="1016683" xmlns="http://eviware.com/soapui/config"/></con:parameters><con:parameterOrder><con:entry>id</con:entry></con:parameterOrder></con:request></con:method></con:resource></con:interface><con:interface xsi:type="con:RestService" id="e91b9e11-e94a-4c66-a80f-d3f578a0575f" wadlVersion="http://wadl.dev.java.net/2009/02" name="" type="rest" xmlns:xsi="http://www.w3.org/2001/XMLSchema-instance"><con:settings/><con:definitionCache/><con:endpoints/><con:resource name="DeleteStudent" path="/api/studentsDetails/{id}" id="bb430863-4a7f-4c1e-91f5-d686dc84cc12"><con:settings/><con:parameters><con:parameter><con:name>id</con:name><con:style>TEMPLATE</con:style></con:parameter></con:parameters><con:method name="DeleteStudent 1" id="5d4da73c-76b0-4e72-acc7-d1f5febf099f" method="DELETE"><con:settings/><con:parameters/><con:representation type="REQUEST"><con:mediaType>application/json</con:mediaType><con:params/></con:representation><con:representation type="RESPONSE"><con:mediaType>application/json; charset=utf-8</con:mediaType><con:status>200</con:status><con:params/><con:element xmlns:ns="http://thetestingworldapi.com/api/studentsDetails/1016627">ns:Response</con:element></con:representation><con:request name="DeleteStudent" id="f13d679b-16f2-4903-a63f-529e01c4bdb9" mediaType="application/json" postQueryString="false"><con:settings><con:setting id="com.eviware.soapui.impl.wsdl.WsdlRequest@request-headers">&lt;xml-fragment/></con:setting></con:settings><con:endpoint>http://thetestingworldapi.com</con:endpoint><con:request/><con:originalUri>http://thetestingworldapi.com/api/studentsDetails/1016627</con:originalUri><con:credentials><con:authType>No Authorization</con:authType></con:credentials><con:jmsConfig JMSDeliveryMode="PERSISTENT"/><con:jmsPropertyConfig/><con:parameters><entry key="id" value="1016627" xmlns="http://eviware.com/soapui/config"/></con:parameters><con:parameterOrder><con:entry>id</con:entry></con:parameterOrder></con:request></con:method></con:resource></con:interface><con:testSuite id="08b1e375-78b0-498c-a682-16c635fb9dc4" name="TestSuite 1"><con:settings/><con:runType>SEQUENTIAL</con:runType><con:testCase id="7098b247-3cc2-4c6a-b909-c19a22f33111" failOnError="true" failTestCaseOnErrors="true" keepSession="false" maxResults="0" name="Students" searchProperties="true"><con:settings/><con:testStep type="restrequest" name="getAllStudents" id="a7064780-0aa9-46ed-ac4c-426a454cc367"><con:settings/><con:config service="http://thetestingworldapi.com" resourcePath="/api/studentsDetails" methodName="getAllStudent" xsi:type="con:RestRequestStep" xmlns:xsi="http://www.w3.org/2001/XMLSchema-instance"><con:restRequest name="getAllStudents" id="089c134a-91b8-4177-993c-fe05aaa1a9a3" mediaType="application/json"><con:settings><con:setting id="com.eviware.soapui.impl.wsdl.WsdlRequest@request-headers">&lt;xml-fragment/></con:setting></con:settings><con:endpoint>http://thetestingworldapi.com</con:endpoint><con:request/><con:originalUri>http://thetestingworldapi.com/api/studentsDetails</con:originalUri><con:credentials><con:authType>No Authorization</con:authType></con:credentials><con:jmsConfig JMSDeliveryMode="PERSISTENT"/><con:jmsPropertyConfig/><con:parameters/></con:restRequest></con:config></con:testStep><con:testStep type="restrequest" name="createStudent" id="54e44df1-6254-450b-bf81-d9007b8469cc"><con:settings/><con:config service="http://thetestingworldapi.com" resourcePath="/api/studentsDetails" methodName="createStudent" xsi:type="con:RestRequestStep" xmlns:xsi="http://www.w3.org/2001/XMLSchema-instance"><con:restRequest name="createStudent" id="cdbfc28a-4740-46f9-8ec6-16778ec45414" mediaType="application/json" postQueryString="false"><con:settings><con:setting id="com.eviware.soapui.impl.wsdl.WsdlRequest@request-headers">&lt;xml-fragment/></con:setting></con:settings><con:endpoint>http://thetestingworldapi.com</con:endpoint><con:request>{
  "id": 1225,
  "first_name": "Ramesh",
  "middle_name": "suresh",
  "last_name": "doubleD",
  "date_of_birth": "20Aug1994"
}</con:request><con:originalUri>http://thetestingworldapi.com/api/studentsDetails</con:originalUri><con:credentials><con:authType>No Authorization</con:authType></con:credentials><con:jmsConfig JMSDeliveryMode="PERSISTENT"/><con:jmsPropertyConfig/><con:parameters/></con:restRequest></con:config></con:testStep><con:testStep type="transfer" name="id" id="ff28a9fd-5680-4b03-b3fe-bfd325aab5f4"><con:settings/><con:config xsi:type="con:PropertyTransfersStep" xmlns:xsi="http://www.w3.org/2001/XMLSchema-instance"><con:transfers setNullOnMissingSource="true" transferTextContent="true" failOnError="true" ignoreEmpty="false" transferToAll="false" entitize="false" transferChildNodes="false"><con:name>id</con:name><con:sourceType>Response</con:sourceType><con:sourceStep>createStudent</con:sourceStep><con:sourcePath>$.id</con:sourcePath><con:targetType>id</con:targetType><con:targetStep>#TestSuite#</con:targetStep><con:type>JSONPATH</con:type><con:upgraded>true</con:upgraded></con:transfers></con:config></con:testStep><con:testStep type="restrequest" name="getSpecificStudent" id="6eed1db1-d855-436e-a5ee-bbcb1c2a34cf"><con:settings/><con:config service="http://thetestingworldapi.com" resourcePath="/api/studentsDetails/{id}" methodName="getStudent" xsi:type="con:RestRequestStep" xmlns:xsi="http://www.w3.org/2001/XMLSchema-instance"><con:restRequest name="getSpecificStudent" id="8f26412b-64b2-4890-a4eb-59379cbbb5b4" mediaType="application/json"><con:settings><con:setting id="com.eviware.soapui.impl.wsdl.WsdlRequest@request-headers">&lt;xml-fragment/></con:setting></con:settings><con:endpoint>http://thetestingworldapi.com</con:endpoint><con:request/><con:originalUri>http://thetestingworldapi.com//studentsDetails/1016618</con:originalUri><con:credentials><con:authType>No Authorization</con:authType></con:credentials><con:jmsConfig JMSDeliveryMode="PERSISTENT"/><con:jmsPropertyConfig/><con:parameters><entry key="id" value="${#TestSuite#id}" xmlns="http://eviware.com/soapui/config"/></con:parameters><con:parameterOrder><con:entry>id</con:entry></con:parameterOrder></con:restRequest></con:config></con:testStep><con:testStep type="restrequest" name="updateStudent" id="96c76e95-1ecd-43d1-aeea-923c11431668"><con:settings/><con:config service="http://thetestingworldapi.com" resourcePath="/api/studentsDetails/{id}" methodName="updateStudent" xsi:type="con:RestRequestStep" xmlns:xsi="http://www.w3.org/2001/XMLSchema-instance"><con:restRequest name="updateStudent" id="31596c05-c3e3-4dba-9f47-e0fcd89325bb" mediaType="application/json" postQueryString="false"><con:settings><con:setting id="com.eviware.soapui.impl.wsdl.WsdlRequest@request-headers">&lt;xml-fragment/></con:setting></con:settings><con:endpoint>http://thetestingworldapi.com</con:endpoint><con:request>{
   "id": ${#TestSuite#id},
   "first_name": "Ramesh",
   "middle_name": "ac",
   "last_name": "doubleD",
   "date_of_birth": "20Aug1994"
}</con:request><con:originalUri>http://thetestingworldapi.com/api/studentsDetails/id</con:originalUri><con:credentials><con:authType>No Authorization</con:authType></con:credentials><con:jmsConfig JMSDeliveryMode="PERSISTENT"/><con:jmsPropertyConfig/><con:parameters><entry key="id" value="${#TestSuite#id}" xmlns="http://eviware.com/soapui/config"/></con:parameters><con:parameterOrder><con:entry>id</con:entry></con:parameterOrder></con:restRequest></con:config></con:testStep><con:testStep type="restrequest" name="getUpdatedStudent" id="f4ddfe3b-5ffd-4338-9452-b1975fa9732f"><con:settings/><con:config service="http://thetestingworldapi.com" resourcePath="/api/studentsDetails/{id}" methodName="updateStudent" xsi:type="con:RestRequestStep" xmlns:xsi="http://www.w3.org/2001/XMLSchema-instance"><con:restRequest name="getUpdatedStudent" id="31596c05-c3e3-4dba-9f47-e0fcd89325bb" mediaType="application/json" postQueryString="false"><con:settings><con:setting id="com.eviware.soapui.impl.wsdl.WsdlRequest@request-headers">&lt;xml-fragment/></con:setting></con:settings><con:endpoint>http://thetestingworldapi.com</con:endpoint><con:request>{
   "id": ${#TestSuite#id},
   "first_name": "Ramesh",
   "middle_name": "abc",
   "last_name": "doubleD",
   "date_of_birth": "20Aug1994"
}</con:request><con:originalUri>http://thetestingworldapi.com/api/studentsDetails/id</con:originalUri><con:credentials><con:authType>No Authorization</con:authType></con:credentials><con:jmsConfig JMSDeliveryMode="PERSISTENT"/><con:jmsPropertyConfig/><con:parameters><entry key="id" value="${#TestSuite#id}" xmlns="http://eviware.com/soapui/config"/></con:parameters><con:parameterOrder><con:entry>id</con:entry></con:parameterOrder></con:restRequest></con:config></con:testStep><con:testStep type="restrequest" name="deleteStudent" id="5c9d2e75-15de-432c-bbd5-723aebf9507c"><con:settings/><con:config service="" resourcePath="/api/studentsDetails/{id}" methodName="DeleteStudent 1" xsi:type="con:RestRequestStep" xmlns:xsi="http://www.w3.org/2001/XMLSchema-instance"><con:restRequest name="deleteStudent" id="f13d679b-16f2-4903-a63f-529e01c4bdb9" mediaType="application/json" postQueryString="false"><con:settings><con:setting id="com.eviware.soapui.impl.wsdl.WsdlRequest@request-headers">&lt;xml-fragment/></con:setting></con:settings><con:endpoint>http://thetestingworldapi.com</con:endpoint><con:request/><con:originalUri>http://thetestingworldapi.com/api/studentsDetails/1016627</con:originalUri><con:credentials><con:authType>No Authorization</con:authType></con:credentials><con:jmsConfig JMSDeliveryMode="PERSISTENT"/><con:jmsPropertyConfig/><con:parameters><entry key="id" value="${#TestSuite#id}" xmlns="http://eviware.com/soapui/config"/></con:parameters><con:parameterOrder><con:entry>id</con:entry></con:parameterOrder></con:restRequest></con:config></con:testStep><con:properties/></con:testCase><con:properties><con:property><con:name>id</con:name><con:value>1016691</con:value></con:property></con:properties></con:testSuite><con:properties/><con:wssContainer/><con:oAuth2ProfileContainer/><con:oAuth1ProfileContainer/></con:soapui-project>